Cooly-0.1.3.dist-info/WHEEL
Cooly-0.1.3.dist-info/RECORD
Cooly-0.1.3.dist-info/METADATA
Cooly-0.1.3.dist-info/metadata.json
Cooly-0.1.3.dist-info/top_level.txt
Cooly-0.1.3.dist-info/dependency_links.txt
Cooly-0.1.3.dist-info/DESCRIPTION.rst
Cooly-0.1.3.dist-info/entry_points.txt
cooly/__init__.py
cooly/fabfile.py
cooly/cli.py
