Metadata-Version: 2.0
Name: Cooly
Version: 0.1.3
Summary: A utility that helps you deploy Python projects.
Home-page: https://github.com/RussellLuo/cooly
Author: RussellLuo
Author-email: luopeng.he@gmail.com
License: MIT
Keywords: Cooly,Python Deployment
Platform: UNKNOWN
Requires-Dist: Fabric (==1.10.1)
Requires-Dist: PyYAML (>=3.10)
Requires-Dist: Click (==4.0)
Requires-Dist: platter (>=1.0-dev)
